logprobs_parser/__init__.py
logprobs_parser/errors.py
logprobs_parser/logprobs.py
logprobs_parser/py.typed
logprobs_parser/result.py
logprobs_parser/types.py
logprobs_parser/providers/gemini.py
logprobs_parser/providers/openai.py
logprobs_parser/providers/together.py
logprobs_parser-0.1.3.dist-info/METADATA
logprobs_parser-0.1.3.dist-info/WHEEL
logprobs_parser-0.1.3.dist-info/top_level.txt
logprobs_parser-0.1.3.dist-info/RECORD
